{"nodes": [{"id": "components_blog_latestnews_tsx", "label": "LatestNews.tsx", "file_type": "code", "source_file": "components/blog/LatestNews.tsx", "source_location": "L1"}, {"id": "latestnews_buildposthref", "label": "buildPostHref()", "file_type": "code", "source_file": "components/blog/LatestNews.tsx", "source_location": "L18"}], "edges": [{"source": "components_blog_latestnews_tsx", "target": "image", "relation": "imports_from", "confidence": "EXTRACTED", "source_file": "components/blog/LatestNews.tsx", "source_location": "L1", "weight": 1.0}, {"source": "components_blog_latestnews_tsx", "target": "link", "relation": "imports_from", "confidence": "EXTRACTED", "source_file": "components/blog/LatestNews.tsx", "source_location": "L2", "weight": 1.0}, {"source": "components_blog_latestnews_tsx", "target": "format", "relation": "imports_from", "confidence": "EXTRACTED", "source_file": "components/blog/LatestNews.tsx", "source_location": "L3", "weight": 1.0}, {"source": "components_blog_latestnews_tsx", "target": "wordpress", "relation": "imports_from", "confidence": "EXTRACTED", "source_file": "components/blog/LatestNews.tsx", "source_location": "L4", "weight": 1.0}, {"source": "components_blog_latestnews_tsx", "target": "components_blog_latestnewsmobilecarousel", "relation": "imports_from", "confidence": "EXTRACTED", "source_file": "components/blog/LatestNews.tsx", "source_location": "L5", "weight": 1.0}, {"source": "components_blog_latestnews_tsx", "target": "components_blog_newslettercard", "relation": "imports_from", "confidence": "EXTRACTED", "source_file": "components/blog/LatestNews.tsx", "source_location": "L6", "weight": 1.0}, {"source": "components_blog_latestnews_tsx", "target": "components_blog_secondarynewscard", "relation": "imports_from", "confidence": "EXTRACTED", "source_file": "components/blog/LatestNews.tsx", "source_location": "L7", "weight": 1.0}, {"source": "components_blog_latestnews_tsx", "target": "latestnews_buildposthref", "relation": "contains", "confidence": "EXTRACTED", "source_file": "components/blog/LatestNews.tsx", "source_location": "L18", "weight": 1.0}]}