{"nodes": [{"id": "lib_parsevideoshowcase_ts", "label": "parseVideoShowcase.ts", "file_type": "code", "source_file": "lib/parseVideoShowcase.ts", "source_location": "L1"}, {"id": "parsevideoshowcase_striptags", "label": "stripTags()", "file_type": "code", "source_file": "lib/parseVideoShowcase.ts", "source_location": "L29"}, {"id": "parsevideoshowcase_parsevideoshowcasefromcontent", "label": "parseVideoShowcaseFromContent()", "file_type": "code", "source_file": "lib/parseVideoShowcase.ts", "source_location": "L33"}], "edges": [{"source": "lib_parsevideoshowcase_ts", "target": "parsevideoshowcase_striptags", "relation": "contains", "confidence": "EXTRACTED", "source_file": "lib/parseVideoShowcase.ts", "source_location": "L29", "weight": 1.0}, {"source": "lib_parsevideoshowcase_ts", "target": "parsevideoshowcase_parsevideoshowcasefromcontent", "relation": "contains", "confidence": "EXTRACTED", "source_file": "lib/parseVideoShowcase.ts", "source_location": "L33", "weight": 1.0}, {"source": "parsevideoshowcase_parsevideoshowcasefromcontent", "target": "parsevideoshowcase_striptags", "relation": "calls", "confidence": "EXTRACTED", "source_file": "lib/parseVideoShowcase.ts", "source_location": "L45", "weight": 1.0}]}